{
  "100": {
    "p0.20-s3x5": {
      "moves": [
        3345,
        3069,
        3665,
        3012,
        3043,
        3313,
        3439,
        3550,
        3363,
        3097
      ],
      "errors": []
    },
    "p0.40-s3x5": {
      "moves": [
        5885,
        5980,
        5820,
        5719,
        5310,
        6035,
        5102,
        5571,
        5641,
        5772
      ],
      "errors": []
    }
  },
  "101": {
    "p0.20-s3x5": {
      "moves": [
        3690,
        3783,
        3422,
        3576,
        3441,
        3561,
        3427,
        3635,
        3402,
        3611
      ],
      "errors": []
    },
    "p0.40-s3x5": {
      "moves": [
        5814,
        5632,
        5882,
        5662,
        5779,
        5844,
        5743,
        5996,
        5862,
        6204
      ],
      "errors": []
    }
  },
  "105": {
    "p0.20-s3x5": {
      "moves": [
        3724,
        3879,
        3925,
        3751,
        3635,
        3493,
        3851,
        3576,
        3729,
        3778
      ],
      "errors": []
    },
    "p0.40-s3x5": {
      "moves": [
        6423,
        6384,
        6243,
        5898,
        6521,
        5851,
        6129,
        6345,
        6026,
        6353
      ],
      "errors": []
    }
  },
  "108": {
    "p0.20-s3x5": {
      "moves": [
        3679,
        3860,
        3678,
        3752,
        4274,
        3888,
        3978,
        3926,
        3754,
        3649
      ],
      "errors": []
    },
    "p0.40-s3x5": {
      "moves": [
        6152,
        6333,
        6811,
        6404,
        6717,
        6296,
        7021,
        6894,
        6620,
        7216
      ],
      "errors": []
    }
  },
  "112": {
    "p0.20-s3x5": {
      "moves": [
        4227,
        4224,
        3789,
        4256,
        3867,
        4132,
        4171,
        4116,
        4369,
        4277
      ],
      "errors": []
    },
    "p0.40-s3x5": {
      "moves": [
        7510,
        6694,
        6904,
        7229,
        7078,
        7432,
        7070,
        7686,
        7557,
        7770
      ],
      "errors": []
    }
  },
  "117": {
    "p0.20-s3x5": {
      "moves": [
        3834,
        3929,
        4352,
        4542,
        4410,
        3833,
        4674,
        4451,
        4437,
        5385
      ],
      "errors": []
    },
    "p0.40-s3x5": {
      "moves": [
        7597,
        7940,
        8220,
        7734,
        7942,
        8072,
        8032,
        7859,
        8105,
        8087
      ],
      "errors": []
    }
  },
  "119": {
    "p0.20-s3x5": {
      "moves": [
        5065,
        4661,
        5149,
        4897,
        5021,
        4982,
        4088,
        4964,
        4344,
        4597
      ],
      "errors": []
    },
    "p0.40-s3x5": {
      "moves": [
        8369,
        8532,
        8337,
        8343,
        8244,
        8103,
        7944,
        8318,
        7727,
        8042
      ],
      "errors": []
    }
  },
  "126": {
    "p0.20-s3x5": {
      "moves": [
        5118,
        6191,
        4966,
        5440,
        5721,
        5182,
        4794,
        6018,
        4236,
        5396
      ],
      "errors": []
    },
    "p0.40-s3x5": {
      "moves": [
        9341,
        8979,
        8874,
        8996,
        8411,
        9232,
        9011,
        8236,
        8644,
        8690
      ],
      "errors": []
    }
  },
  "129": {
    "p0.20-s3x5": {
      "moves": [
        5347,
        5345,
        5813,
        6090,
        4982,
        5549,
        6079,
        5846,
        5882,
        5640
      ],
      "errors": []
    },
    "p0.40-s3x5": {
      "moves": [
        10142,
        9024,
        9908,
        9590,
        9403,
        9660,
        9518,
        9132,
        8884,
        8858
      ],
      "errors": []
    }
  },
  "132": {
    "p0.20-s3x5": {
      "moves": [
        6265,
        5397,
        5636,
        5908,
        6059,
        5655,
        5281,
        5822,
        5548,
        5483
      ],
      "errors": []
    },
    "p0.40-s3x5": {
      "moves": [
        9856,
        9910,
        10057,
        9986,
        9132,
        9425,
        9213,
        9246,
        10643,
        9507
      ],
      "errors": []
    }
  },
  "133": {
    "p0.20-s3x5": {
      "moves": [
        5979,
        6299,
        5508,
        5495,
        6414,
        5617,
        6395,
        5083,
        6146,
        5964
      ],
      "errors": []
    },
    "p0.40-s3x5": {
      "moves": [
        10256,
        9228,
        9663,
        9578,
        10097,
        9456,
        9572,
        10583,
        10177,
        10318
      ],
      "errors": []
    }
  },
  "139": {
    "p0.20-s3x5": {
      "moves": [
        5962,
        6592,
        6295,
        6031,
        6252,
        6783,
        6677,
        7364,
        6202,
        5758
      ],
      "errors": []
    },
    "p0.40-s3x5": {
      "moves": [
        11387,
        11257,
        10668,
        11604,
        11184,
        10984,
        11292,
        11384,
        10989,
        10700
      ],
      "errors": []
    }
  },
  "145": {
    "p0.20-s3x5": {
      "moves": [
        6624,
        6358,
        6217,
        6264,
        7588,
        6730,
        6218,
        7003,
        6734,
        7141
      ],
      "errors": []
    },
    "p0.40-s3x5": {
      "moves": [
        10919,
        12274,
        11842,
        11341,
        11572,
        11578,
        11800,
        11658,
        11176,
        12172
      ],
      "errors": []
    }
  },
  "147": {
    "p0.20-s3x5": {
      "moves": [
        6080,
        7991,
        6755,
        7856,
        7499,
        6367,
        6939,
        7246,
        6554,
        6811
      ],
      "errors": []
    },
    "p0.40-s3x5": {
      "moves": [
        12696,
        12335,
        12385,
        12103,
        11304,
        12063,
        11625,
        11724,
        11752,
        11123
      ],
      "errors": []
    }
  },
  "148": {
    "p0.20-s3x5": {
      "moves": [
        6958,
        7281,
        7685,
        7007,
        6330,
        7321,
        7189,
        6682,
        6726,
        7536
      ],
      "errors": []
    },
    "p0.40-s3x5": {
      "moves": [
        12440,
        12064,
        11514,
        12650,
        12756,
        11720,
        12260,
        12860,
        12781,
        12907
      ],
      "errors": []
    }
  },
  "154": {
    "p0.20-s3x5": {
      "moves": [
        8128,
        7312,
        7669,
        7485,
        7962,
        8253,
        8447,
        7937,
        8448,
        8432
      ],
      "errors": []
    },
    "p0.40-s3x5": {
      "moves": [
        13362,
        13261,
        14040,
        13963,
        13075,
        11715,
        13900,
        13423,
        13176,
        12765
      ],
      "errors": []
    }
  },
  "156": {
    "p0.20-s3x5": {
      "moves": [
        8005,
        7590,
        7772,
        8407,
        7741,
        7181,
        8058,
        7722,
        9286,
        8131
      ],
      "errors": []
    },
    "p0.40-s3x5": {
      "moves": [
        13638,
        13540,
        13504,
        13634,
        13247,
        14228,
        13637,
        12995,
        13944,
        13179
      ],
      "errors": []
    }
  },
  "181": {
    "p0.20-s3x5": {
      "moves": [
        10640,
        12458,
        11591,
        10625,
        12841,
        9985,
        9787,
        11104,
        10046,
        10410
      ],
      "errors": []
    },
    "p0.40-s3x5": {
      "moves": [
        17787,
        18603,
        18002,
        18429,
        19518,
        18081,
        18425,
        17025,
        18686,
        18963
      ],
      "errors": []
    }
  },
  "187": {
    "p0.20-s3x5": {
      "moves": [
        10016,
        11001,
        12290,
        11038,
        10685,
        9670,
        11222,
        10169,
        11759,
        10950
      ],
      "errors": []
    },
    "p0.40-s3x5": {
      "moves": [
        19865,
        20344,
        18287,
        19363,
        18328,
        19072,
        18815,
        19515,
        18396,
        20980
      ],
      "errors": []
    }
  },
  "188": {
    "p0.20-s3x5": {
      "moves": [
        10801,
        10456,
        11199,
        11015,
        10891,
        10922,
        11402,
        12886,
        10629,
        11373
      ],
      "errors": []
    },
    "p0.40-s3x5": {
      "moves": [
        21225,
        20259,
        18711,
        20011,
        20830,
        19304,
        18908,
        18320,
        19012,
        20027
      ],
      "errors": []
    }
  },
  "191": {
    "p0.20-s3x5": {
      "moves": [
        11825,
        10017,
        10668,
        13207,
        12073,
        12057,
        12295,
        11667,
        10430,
        12449
      ],
      "errors": []
    },
    "p0.40-s3x5": {
      "moves": [
        21347,
        19489,
        21334,
        18969,
        20469,
        19759,
        21041,
        19512,
        19600,
        19052
      ],
      "errors": []
    }
  },
  "200": {
    "p0.20-s3x5": {
      "moves": [
        11989,
        13585,
        13805,
        12466,
        14112,
        12799,
        13894,
        12113,
        11784,
        11846
      ],
      "errors": []
    },
    "p0.40-s3x5": {
      "moves": [
        23534,
        22519,
        21406,
        22667,
        21554,
        23188,
        22739,
        23451,
        21921,
        21893
      ],
      "errors": []
    }
  },
  "204": {
    "p0.20-s3x5": {
      "moves": [
        14417,
        13929,
        14420,
        13091,
        14333,
        14149,
        12495,
        14170,
        13110,
        12545
      ],
      "errors": []
    },
    "p0.40-s3x5": {
      "moves": [
        23338,
        23120,
        22597,
        21603,
        22552,
        23155,
        23702,
        21969,
        22722,
        23222
      ],
      "errors": []
    }
  },
  "205": {
    "p0.20-s3x5": {
      "moves": [
        11759,
        13351,
        14679,
        12993,
        14241,
        13329,
        11652,
        12697,
        11633,
        13856
      ],
      "errors": []
    },
    "p0.40-s3x5": {
      "moves": [
        23186,
        22579,
        24097,
        20679,
        22732,
        23029,
        23542,
        23566,
        23296,
        20481
      ],
      "errors": []
    }
  },
  "209": {
    "p0.20-s3x5": {
      "moves": [
        13743,
        13305,
        13103,
        13894,
        14924,
        14689,
        14384,
        16319,
        13676,
        13654
      ],
      "errors": []
    },
    "p0.40-s3x5": {
      "moves": [
        24690,
        22651,
        22709,
        23361,
        23964,
        24353,
        25161,
        25754,
        24320,
        26462
      ],
      "errors": []
    }
  },
  "216": {
    "p0.20-s3x5": {
      "moves": [
        13521,
        14642,
        14106,
        13899,
        14147,
        14604,
        14301,
        16896,
        14266,
        15164
      ],
      "errors": []
    },
    "p0.40-s3x5": {
      "moves": [
        25791,
        25205,
        26601,
        26176,
        26055,
        25757,
        26015,
        25470,
        24871,
        26741
      ],
      "errors": []
    }
  },
  "219": {
    "p0.20-s3x5": {
      "moves": [
        14371,
        15400,
        14074,
        15559,
        14798,
        15523,
        16664,
        14120,
        13861,
        15984
      ],
      "errors": []
    },
    "p0.40-s3x5": {
      "moves": [
        26987,
        26376,
        27244,
        25664,
        26843,
        24934,
        26116,
        26971,
        25345,
        25748
      ],
      "errors": []
    }
  },
  "222": {
    "p0.20-s3x5": {
      "moves": [
        15023,
        15426,
        15511,
        15238,
        15249,
        14924,
        14870,
        15277,
        15887,
        15638
      ],
      "errors": []
    },
    "p0.40-s3x5": {
      "moves": [
        26277,
        26044,
        24230,
        25956,
        27417,
        27210,
        27396,
        26142,
        25982,
        25821
      ],
      "errors": []
    }
  },
  "225": {
    "p0.20-s3x5": {
      "moves": [
        15325,
        17731,
        16533,
        15831,
        15158,
        14775,
        14162,
        14061,
        15452,
        15726
      ],
      "errors": []
    },
    "p0.40-s3x5": {
      "moves": [
        26083,
        26189,
        26871,
        27912,
        26717,
        29903,
        29271,
        27023,
        26753,
        27142
      ],
      "errors": []
    }
  },
  "234": {
    "p0.20-s3x5": {
      "moves": [
        17724,
        17149,
        18694,
        17825,
        16431,
        17231,
        17389,
        15882,
        16308,
        17068
      ],
      "errors": []
    },
    "p0.40-s3x5": {
      "moves": [
        30483,
        30063,
        27564,
        29432,
        29719,
        29354,
        28469,
        27911,
        28681,
        30821
      ],
      "errors": []
    }
  },
  "243": {
    "p0.20-s3x5": {
      "moves": [
        16701,
        18184,
        19095,
        19026,
        17828,
        16323,
        17128,
        16827,
        18474,
        18466
      ],
      "errors": []
    },
    "p0.40-s3x5": {
      "moves": [
        33301,
        29693,
        30734,
        32369,
        30718,
        33264,
        32249,
        31871,
        30820,
        30223
      ],
      "errors": []
    }
  },
  "253": {
    "p0.20-s3x5": {
      "moves": [
        20001,
        18571,
        19233,
        19391,
        20995,
        20763,
        21380,
        20930,
        18697,
        20524
      ],
      "errors": []
    },
    "p0.40-s3x5": {
      "moves": [
        32342,
        32683,
        33861,
        34468,
        31202,
        31706,
        35665,
        35422,
        31978,
        33389
      ],
      "errors": []
    }
  },
  "257": {
    "p0.20-s3x5": {
      "moves": [
        18838,
        20119,
        20532,
        21397,
        19626,
        19928,
        18522,
        22746,
        19907,
        21274
      ],
      "errors": []
    },
    "p0.40-s3x5": {
      "moves": [
        33878,
        33790,
        35729,
        34220,
        37095,
        37305,
        34399,
        34053,
        36644,
        34989
      ],
      "errors": []
    }
  },
  "263": {
    "p0.20-s3x5": {
      "moves": [
        21931,
        23283,
        20236,
        22639,
        21721,
        22692,
        21013,
        21511,
        22973,
        22291
      ],
      "errors": []
    },
    "p0.40-s3x5": {
      "moves": [
        37389,
        37105,
        36566,
        36550,
        37158,
        38161,
        39457,
        38419,
        34678,
        36064
      ],
      "errors": []
    }
  },
  "267": {
    "p0.20-s3x5": {
      "moves": [
        25085,
        20763,
        22661,
        20074,
        25512,
        26229,
        21855,
        19979,
        20772,
        23259
      ],
      "errors": []
    },
    "p0.40-s3x5": {
      "moves": [
        40664,
        36604,
        39909,
        38945,
        36903,
        39099,
        39187,
        39083,
        38513,
        35447
      ],
      "errors": []
    }
  },
  "270": {
    "p0.20-s3x5": {
      "moves": [
        25242,
        21711,
        20723,
        23400,
        21272,
        21328,
        23045,
        22541,
        23721,
        22410
      ],
      "errors": []
    },
    "p0.40-s3x5": {
      "moves": [
        39636,
        38766,
        39358,
        40365,
        40252,
        38565,
        41342,
        38762,
        41561,
        38324
      ],
      "errors": []
    }
  },
  "274": {
    "p0.20-s3x5": {
      "moves": [
        21738,
        22869,
        22193,
        24932,
        23578,
        25726,
        22987,
        22077,
        24285,
        23277
      ],
      "errors": []
    },
    "p0.40-s3x5": {
      "moves": [
        40837,
        44789,
        38586,
        38832,
        41659,
        41243,
        38125,
        42709,
        41491,
        42197
      ],
      "errors": []
    }
  },
  "283": {
    "p0.20-s3x5": {
      "moves": [
        23214,
        22912,
        26554,
        25489,
        26915,
        25265,
        23100,
        24138,
        26353,
        23857
      ],
      "errors": []
    },
    "p0.40-s3x5": {
      "moves": [
        44169,
        40409,
        42352,
        43406,
        42412,
        44996,
        37519,
        40451,
        43891,
        41779
      ],
      "errors": []
    }
  },
  "288": {
    "p0.20-s3x5": {
      "moves": [
        26394,
        22726,
        27652,
        25197,
        25537,
        27758,
        26720,
        24870,
        23561,
        26893
      ],
      "errors": []
    },
    "p0.40-s3x5": {
      "moves": [
        41506,
        44804,
        44005,
        44475,
        44865,
        41764,
        45291,
        44299,
        46061,
        44268
      ],
      "errors": []
    }
  },
  "290": {
    "p0.20-s3x5": {
      "moves": [
        30435,
        24404,
        24873,
        25257,
        24763,
        25939,
        26902,
        26160,
        27061,
        24751
      ],
      "errors": []
    },
    "p0.40-s3x5": {
      "moves": [
        43466,
        46127,
        45821,
        43470,
        45644,
        45236,
        43584,
        44242,
        41384,
        47479
      ],
      "errors": []
    }
  },
  "291": {
    "p0.20-s3x5": {
      "moves": [
        24740,
        26032,
        27436,
        27529,
        25079,
        25026,
        26461,
        30131,
        25139,
        27791
      ],
      "errors": []
    },
    "p0.40-s3x5": {
      "moves": [
        43045,
        41818,
        45526,
        46979,
        42998,
        45727,
        46675,
        48079,
        47404,
        49572
      ],
      "errors": []
    }
  },
  "295": {
    "p0.20-s3x5": {
      "moves": [
        25731,
        24836,
        27908,
        24854,
        24427,
        25758,
        25146,
        27601,
        28226,
        27347
      ],
      "errors": []
    },
    "p0.40-s3x5": {
      "moves": [
        46151,
        48004,
        49229,
        46610,
        49767,
        48164,
        45774,
        46264,
        45603,
        48866
      ],
      "errors": []
    }
  },
  "296": {
    "p0.20-s3x5": {
      "moves": [
        26488,
        26522,
        29771,
        26429,
        27054,
        26248,
        27659,
        28882,
        25870,
        25511
      ],
      "errors": []
    },
    "p0.40-s3x5": {
      "moves": [
        48729,
        47922,
        51524,
        47934,
        44109,
        48895,
        50013,
        46584,
        47840,
        42961
      ],
      "errors": []
    }
  },
  "298": {
    "p0.20-s3x5": {
      "moves": [
        25208,
        26442,
        24806,
        24977,
        30638,
        25475,
        29232,
        28001,
        24904,
        29980
      ],
      "errors": []
    },
    "p0.40-s3x5": {
      "moves": [
        46357,
        47774,
        46272,
        46962,
        47131,
        45303,
        45152,
        47448,
        49450,
        47101
      ],
      "errors": []
    }
  },
  "308": {
    "p0.20-s3x5": {
      "moves": [
        29974,
        25979,
        28833,
        29929,
        30660,
        26486,
        29970,
        27080,
        32979,
        30689
      ],
      "errors": []
    },
    "p0.40-s3x5": {
      "moves": [
        48473,
        48178,
        50170,
        52909,
        49029,
        51564,
        53152,
        51989,
        53700,
        50853
      ],
      "errors": []
    }
  },
  "324": {
    "p0.20-s3x5": {
      "moves": [
        30809,
        30993,
        30505,
        31469,
        31366,
        35038,
        32676,
        35118,
        35503,
        32082
      ],
      "errors": []
    },
    "p0.40-s3x5": {
      "moves": [
        58247,
        58188,
        55687,
        57514,
        55874,
        54347,
        59806,
        58752,
        56748,
        60243
      ],
      "errors": []
    }
  },
  "327": {
    "p0.20-s3x5": {
      "moves": [
        34538,
        32269,
        33165,
        30646,
        31900,
        32435,
        32563,
        32699,
        32536,
        30689
      ],
      "errors": []
    },
    "p0.40-s3x5": {
      "moves": [
        61947,
        56783,
        50658,
        56795,
        58815,
        56490,
        55962,
        53637,
        59085,
        52118
      ],
      "errors": []
    }
  },
  "331": {
    "p0.20-s3x5": {
      "moves": [
        35337,
        33072,
        34300,
        36193,
        33390,
        32650,
        37084,
        32743,
        35259,
        36351
      ],
      "errors": []
    },
    "p0.40-s3x5": {
      "moves": [
        55198,
        56627,
        54198,
        58365,
        57672,
        56618,
        58928,
        60961,
        55850,
        57434
      ],
      "errors": []
    }
  },
  "332": {
    "p0.20-s3x5": {
      "moves": [
        31503,
        31961,
        34815,
        32159,
        31624,
        33346,
        35292,
        31812,
        32039,
        35414
      ],
      "errors": []
    },
    "p0.40-s3x5": {
      "moves": [
        59875,
        55195,
        57480,
        59369,
        54712,
        58561,
        56232,
        53089,
        60225,
        59651
      ],
      "errors": []
    }
  },
  "334": {
    "p0.20-s3x5": {
      "moves": [
        35407,
        31276,
        34034,
        31833,
        32300,
        33952,
        36881,
        34311,
        31891,
        36814
      ],
      "errors": []
    },
    "p0.40-s3x5": {
      "moves": [
        59467,
        55208,
        60034,
        57451,
        57064,
        59570,
        60188,
        61988,
        56686,
        59625
      ],
      "errors": []
    }
  },
  "339": {
    "p0.20-s3x5": {
      "moves": [
        33754,
        34565,
        32547,
        35215,
        37386,
        38673,
        31993,
        39887,
        35023,
        39478
      ],
      "errors": []
    },
    "p0.40-s3x5": {
      "moves": [
        64256,
        59954,
        62233,
        57367,
        58973,
        64400,
        65682,
        59666,
        63090,
        61530
      ],
      "errors": []
    }
  },
  "341": {
    "p0.20-s3x5": {
      "moves": [
        34663,
        38253,
        33574,
        33370,
        31479,
        37502,
        37313,
        34135,
        33201,
        37807
      ],
      "errors": []
    },
    "p0.40-s3x5": {
      "moves": [
        64374,
        61543,
        61423,
        59434,
        62676,
        62235,
        64719,
        63779,
        55519,
        62340
      ],
      "errors": []
    }
  },
  "353": {
    "p0.20-s3x5": {
      "moves": [
        34616,
        35075,
        35205,
        35832,
        33535,
        39901,
        43753,
        33501,
        35679,
        41113
      ],
      "errors": []
    },
    "p0.40-s3x5": {
      "moves": [
        65226,
        66989,
        65715,
        64555,
        71116,
        62948,
        72516,
        68419,
        63945,
        66875
      ],
      "errors": []
    }
  },
  "366": {
    "p0.20-s3x5": {
      "moves": [
        37890,
        41090,
        41284,
        43704,
        41604,
        36156,
        40322,
        39544,
        42991,
        45054
      ],
      "errors": []
    },
    "p0.40-s3x5": {
      "moves": [
        72372,
        75122,
        65967,
        75443,
        72683,
        74488,
        74931,
        67458,
        74534,
        66906
      ],
      "errors": []
    }
  },
  "369": {
    "p0.20-s3x5": {
      "moves": [
        39332,
        41458,
        39322,
        39401,
        40385,
        44950,
        36679,
        42009,
        40859,
        43150
      ],
      "errors": []
    },
    "p0.40-s3x5": {
      "moves": [
        76041,
        73077,
        68146,
        72886,
        69067,
        72935,
        75979,
        76913,
        73308,
        67695
      ],
      "errors": []
    }
  },
  "374": {
    "p0.20-s3x5": {
      "moves": [
        38063,
        38486,
        42343,
        40515,
        41047,
        39165,
        45029,
        43122,
        43165,
        40775
      ],
      "errors": []
    },
    "p0.40-s3x5": {
      "moves": [
        68514,
        67821,
        70969,
        71795,
        74819,
        68880,
        70358,
        78355,
        75967,
        77077
      ],
      "errors": []
    }
  },
  "385": {
    "p0.20-s3x5": {
      "moves": [
        42148,
        42347,
        43494,
        44294,
        46952,
        44998,
        41623,
        46327,
        42855,
        47919
      ],
      "errors": []
    },
    "p0.40-s3x5": {
      "moves": [
        82731,
        76724,
        81595,
        76752,
        84364,
        78665,
        76328,
        82433,
        82659,
        79668
      ],
      "errors": []
    }
  },
  "386": {
    "p0.20-s3x5": {
      "moves": [
        42950,
        44288,
        44156,
        43207,
        41905,
        47682,
        45643,
        44837,
        46262,
        42332
      ],
      "errors": []
    },
    "p0.40-s3x5": {
      "moves": [
        77554,
        81747,
        82172,
        83176,
        75811,
        79680,
        73687,
        76979,
        79153,
        86105
      ],
      "errors": []
    }
  },
  "389": {
    "p0.20-s3x5": {
      "moves": [
        43692,
        42311,
        43872,
        42013,
        47904,
        42696,
        43901,
        45218,
        44649,
        45027
      ],
      "errors": []
    },
    "p0.40-s3x5": {
      "moves": [
        88564,
        77253,
        80141,
        80154,
        78015,
        81620,
        75915,
        83606,
        86976,
        81043
      ],
      "errors": []
    }
  },
  "418": {
    "p0.20-s3x5": {
      "moves": [
        49889,
        51683,
        54236,
        51272,
        48734,
        52998,
        52184,
        49620,
        55986,
        56686
      ],
      "errors": []
    },
    "p0.40-s3x5": {
      "moves": [
        96961,
        92745,
        91751,
        87298,
        94406,
        95134,
        92773,
        95750,
        95366,
        95615
      ],
      "errors": []
    }
  },
  "429": {
    "p0.20-s3x5": {
      "moves": [
        51634,
        57621,
        51443,
        59281,
        60572,
        51307,
        57628,
        57242,
        57883,
        52102
      ],
      "errors": []
    },
    "p0.40-s3x5": {
      "moves": [
        94275,
        87035,
        101069,
        95528,
        90722,
        100585,
        90739,
        96902,
        101382,
        97952
      ],
      "errors": []
    }
  },
  "430": {
    "p0.20-s3x5": {
      "moves": [
        54391,
        54186,
        51825,
        57203,
        58653,
        52051,
        55177,
        53301,
        54970,
        58682
      ],
      "errors": []
    },
    "p0.40-s3x5": {
      "moves": [
        99702,
        98185,
        87573,
        95758,
        98071,
        96827,
        94881,
        96376,
        95997,
        95129
      ],
      "errors": []
    }
  },
  "431": {
    "p0.20-s3x5": {
      "moves": [
        54431,
        53268,
        53834,
        54849,
        50650,
        55820,
        63340,
        55192,
        59301,
        53551
      ],
      "errors": []
    },
    "p0.40-s3x5": {
      "moves": [
        93809,
        96243,
        100347,
        97274,
        95573,
        93868,
        101521,
        99728,
        99842,
        95090
      ],
      "errors": []
    }
  },
  "441": {
    "p0.20-s3x5": {
      "moves": [
        57257,
        58635,
        62011,
        58064,
        55704,
        66273,
        58385,
        54411,
        58073,
        64349
      ],
      "errors": []
    },
    "p0.40-s3x5": {
      "moves": [
        103719,
        100774,
        105129,
        99114,
        99614,
        103443,
        102584,
        108503,
        97519,
        104157
      ],
      "errors": []
    }
  },
  "448": {
    "p0.20-s3x5": {
      "moves": [
        56199,
        57847,
        64356,
        60779,
        61766,
        56705,
        57613,
        56173,
        59215,
        67369
      ],
      "errors": []
    },
    "p0.40-s3x5": {
      "moves": [
        100833,
        101444,
        110665,
        97537,
        107305,
        109492,
        107277,
        103992,
        111880,
        103850
      ],
      "errors": []
    }
  },
  "449": {
    "p0.20-s3x5": {
      "moves": [
        59206,
        63219,
        58526,
        67817,
        64765,
        56590,
        57488,
        62124,
        58845,
        55043
      ],
      "errors": []
    },
    "p0.40-s3x5": {
      "moves": [
        104354,
        105449,
        102012,
        97517,
        107366,
        110211,
        108475,
        111208,
        105470,
        108504
      ],
      "errors": []
    }
  },
  "454": {
    "p0.20-s3x5": {
      "moves": [
        65556,
        56033,
        56002,
        59229,
        58671,
        64788,
        62751,
        62656,
        57680,
        57190
      ],
      "errors": []
    },
    "p0.40-s3x5": {
      "moves": [
        99605,
        115206,
        110476,
        112775,
        106260,
        111316,
        107005,
        104719,
        111056,
        108904
      ],
      "errors": []
    }
  },
  "455": {
    "p0.20-s3x5": {
      "moves": [
        59976,
        55900,
        59735,
        56352,
        58504,
        64987,
        63466,
        59658,
        59134,
        64613
      ],
      "errors": []
    },
    "p0.40-s3x5": {
      "moves": [
        109309,
        106700,
        103962,
        105292,
        100976,
        99395,
        104169,
        107041,
        110689,
        108023
      ],
      "errors": []
    }
  },
  "456": {
    "p0.20-s3x5": {
      "moves": [
        66065,
        64779,
        59810,
        57972,
        56761,
        60817,
        64745,
        59613,
        64515,
        57364
      ],
      "errors": []
    },
    "p0.40-s3x5": {
      "moves": [
        109748,
        110748,
        106946,
        104426,
        102777,
        109167,
        108555,
        110520,
        110854,
        116370
      ],
      "errors": []
    }
  },
  "458": {
    "p0.20-s3x5": {
      "moves": [
        65240,
        65303,
        64237,
        64206,
        58396,
        61778,
        63662,
        61527,
        66933,
        65092
      ],
      "errors": []
    },
    "p0.40-s3x5": {
      "moves": [
        113140,
        101105,
        115701,
        104690,
        116156,
        110865,
        116453,
        109410,
        113219,
        106870
      ],
      "errors": []
    }
  },
  "460": {
    "p0.20-s3x5": {
      "moves": [
        63664,
        79000,
        63771,
        58314,
        69634,
        63149,
        55774,
        63027,
        60080,
        61488
      ],
      "errors": []
    },
    "p0.40-s3x5": {
      "moves": [
        103195,
        115130,
        112203,
        116364,
        115870,
        113630,
        109098,
        116318,
        113376,
        117730
      ],
      "errors": []
    }
  },
  "463": {
    "p0.20-s3x5": {
      "moves": [
        65715,
        68600,
        64942,
        62337,
        62675,
        59816,
        70621,
        65826,
        61475,
        70146
      ],
      "errors": []
    },
    "p0.40-s3x5": {
      "moves": [
        115932,
        110542,
        103922,
        114117,
        120202,
        111104,
        114363,
        112898,
        116121,
        117153
      ],
      "errors": []
    }
  },
  "466": {
    "p0.20-s3x5": {
      "moves": [
        63696,
        60116,
        65417,
        69227,
        59085,
        69338,
        69454,
        64272,
        68308,
        66306
      ],
      "errors": []
    },
    "p0.40-s3x5": {
      "moves": [
        122089,
        108964,
        104420,
        112570,
        111681,
        117557,
        112306,
        116248,
        117698,
        110436
      ],
      "errors": []
    }
  },
  "468": {
    "p0.20-s3x5": {
      "moves": [
        62338,
        63613,
        64340,
        64484,
        75345,
        65962,
        62918,
        59358,
        70861,
        59640
      ],
      "errors": []
    },
    "p0.40-s3x5": {
      "moves": [
        124230,
        119954,
        111643,
        107490,
        113614,
        120912,
        117164,
        113970,
        108613,
        114502
      ],
      "errors": []
    }
  },
  "472": {
    "p0.20-s3x5": {
      "moves": [
        63819,
        65634,
        61010,
        67653,
        67432,
        64596,
        68164,
        61834,
        75707,
        67439
      ],
      "errors": []
    },
    "p0.40-s3x5": {
      "moves": [
        113310,
        115899,
        112234,
        118915,
        115134,
        118392,
        120099,
        117980,
        117699,
        112707
      ],
      "errors": []
    }
  },
  "474": {
    "p0.20-s3x5": {
      "moves": [
        70185,
        62286,
        78735,
        61176,
        69236,
        63637,
        73875,
        65424,
        65599,
        69496
      ],
      "errors": []
    },
    "p0.40-s3x5": {
      "moves": [
        116182,
        127148,
        121981,
        114028,
        115958,
        113406,
        120612,
        116475,
        109570,
        118041
      ],
      "errors": []
    }
  },
  "482": {
    "p0.20-s3x5": {
      "moves": [
        63900,
        70490,
        74457,
        61617,
        67093,
        69985,
        62494,
        64981,
        74454,
        69773
      ],
      "errors": []
    },
    "p0.40-s3x5": {
      "moves": [
        120522,
        116406,
        117068,
        118909,
        127310,
        119851,
        129284,
        119083,
        120244,
        121233
      ],
      "errors": []
    }
  },
  "491": {
    "p0.20-s3x5": {
      "moves": [
        72015,
        73783,
        72702,
        69061,
        67914,
        65985,
        66152,
        68988,
        76298,
        71571
      ],
      "errors": []
    },
    "p0.40-s3x5": {
      "moves": [
        130475,
        129166,
        118207,
        135212,
        119170,
        120522,
        116164,
        129039,
        113363,
        128642
      ],
      "errors": []
    }
  },
  "493": {
    "p0.20-s3x5": {
      "moves": [
        73508,
        81918,
        84932,
        80609,
        67130,
        77191,
        71952,
        86592,
        73077,
        76068
      ],
      "errors": []
    },
    "p0.40-s3x5": {
      "moves": [
        127898,
        118224,
        131690,
        124682,
        129050,
        115563,
        124689,
        128363,
        123323,
        125135
      ],
      "errors": []
    }
  },
  "494": {
    "p0.20-s3x5": {
      "moves": [
        70481,
        73426,
        82837,
        66888,
        72223,
        76463,
        72991,
        70236,
        69643,
        67929
      ],
      "errors": []
    },
    "p0.40-s3x5": {
      "moves": [
        122265,
        123972,
        129516,
        129270,
        124699,
        129153,
        121449,
        125010,
        124795,
        119232
      ],
      "errors": []
    }
  },
  "497": {
    "p0.20-s3x5": {
      "moves": [
        72954,
        80328,
        68157,
        71619,
        66310,
        79609,
        72261,
        76658,
        77775,
        74644
      ],
      "errors": []
    },
    "p0.40-s3x5": {
      "moves": [
        130748,
        126917,
        135923,
        138833,
        134258,
        134381,
        125161,
        120814,
        123724,
        136118
      ],
      "errors": []
    }
  }
}